WebScraperPackage/__init__.py
WebScraperPackage/scraper.py
WebScraperPackage-0.1.dist-info/LICENSE
WebScraperPackage-0.1.dist-info/METADATA
WebScraperPackage-0.1.dist-info/WHEEL
WebScraperPackage-0.1.dist-info/top_level.txt
WebScraperPackage-0.1.dist-info/RECORD
